ez_setup.py
setup.py
SQLiteFKTG4SA.egg-info/PKG-INFO
SQLiteFKTG4SA.egg-info/SOURCES.txt
SQLiteFKTG4SA.egg-info/dependency_links.txt
SQLiteFKTG4SA.egg-info/requires.txt
SQLiteFKTG4SA.egg-info/top_level.txt
SQLiteFKTG4SA.egg-info/zip-safe
sqlitefktg4sa/__init__.py
sqlitefktg4sa/core.py
tests/orm.py
tests/test_elixir.py
tests/test_sq.py