Metadata-Version: 1.0
Name: SQLiteFKTG4SA
Version: 0.1.1
Summary: SQLite Foreign Key Trigger Generator for SQLAlchemy
Home-page: http://code.google.com/p/sqlitefktg4sa/
Author: Randy Syring
Author-email: randy@rcs-comp.com
License: BSD
Platform: UNKNOWN
Classifier: Development Status :: 4 - Beta
Classifier: Intended Audience :: Developers
Classifier: License :: OSI Approved :: BSD License
